tensorboard_plugin_geometry/__init__.py
tensorboard_plugin_geometry/data_server.py
tensorboard_plugin_geometry/metadata.py
tensorboard_plugin_geometry/plugin.py
tensorboard_plugin_geometry/plugin_data_pb2.py
tensorboard_plugin_geometry/summary.py
tensorboard_plugin_geometry/summary_test.py
tensorboard_plugin_geometry/tag_server.py
tensorboard_plugin_geometry/update_test.py
tensorboard_plugin_geometry/static/bundle/index.js
tensorboard_plugin_geometry/static/bundle/render.js
tensorboard_plugin_geometry/static/bundle/assets/MaterialIcons-Regular.eot
tensorboard_plugin_geometry/static/bundle/assets/MaterialIcons-Regular.ttf
tensorboard_plugin_geometry/static/bundle/assets/MaterialIcons-Regular.woff
tensorboard_plugin_geometry/static/bundle/assets/MaterialIcons-Regular.woff2
tensorboard_plugin_geometry-0.6.0.dist-info/LICENSE
tensorboard_plugin_geometry-0.6.0.dist-info/METADATA
tensorboard_plugin_geometry-0.6.0.dist-info/WHEEL
tensorboard_plugin_geometry-0.6.0.dist-info/entry_points.txt
tensorboard_plugin_geometry-0.6.0.dist-info/top_level.txt
tensorboard_plugin_geometry-0.6.0.dist-info/RECORD
