Metadata-Version: 2.1
Name: tensorboard-plugin-geometry
Version: 0.6.0
Summary: Tensorboard plugin to visualize 3D data with 3D features.
Home-page: https://github.com/jannessm/tensorboard-plugin-geometry
Author: Jannes Magnusson
Author-email: j-magnusson@t-online.de
License: GNU GPL
Keywords: tensorboard mesh geometries plugin
Platform: UNKNOWN
Requires-Dist: torch
Requires-Dist: tensorboard (<=2.4.1,>=2.3.0)
Requires-Dist: six
Requires-Dist: werkzeug
Requires-Dist: numpy
